{
    "href": "/game/camp_buddy_scoutmaster_season",
    "MSG": {
        "id": "2130941102",
        "title": "Camp Buddy: Scoutmaster Season",
        "slug": "camp_buddy_scoutmaster_season",
        "thumb_id": "8eb55b4733ad19788f2d49c377b9bbac81b79d2ef9e6315b8e0f1d284eee2b10",
        "bg_id": "7903a311362f7f825dbc64b1b8a34cedd8b149d82fcefac4143dd58df9889b0d",
        "url": "https://www.gog.com/en/game/camp_buddy_scoutmaster_season",
        "developer": "BLits Games",
        "publisher": "BLits Games",
        "category": "Simulation",
        "uploading": "0",
        "last_upload": "1710836015",
        "votes": "1",
        "files": {
            "GAME": [
                {
                    "name": "setup_camp_buddy_scoutmaster_season_1.5.4_(69708)-1.bin",
                    "size": "4293959678"
                },
                {
                    "name": "setup_camp_buddy_scoutmaster_season_1.5.4_(69708)-2.bin",
                    "size": "2237202143"
                },
                {
                    "name": "setup_camp_buddy_scoutmaster_season_1.5.4_(69708).exe",
                    "size": "1017680"
                }
            ],
            "PATCHES": [],
            "GOODIES": []
        },
        "links": {
            "GAME": [
                {
                    "slug": "1fichier",
                    "name": "1fichier",
                    "icon": "<img src=\"/static/img/hoster_logos/1fichier.svg\" class=\"fac-hoster\">",
                    "links": [
                        {
                            "name": "https://filecrypt.cc/Container/8820D17B50",
                            "link": "https://filecrypt.cc/Container/8820D17B50"
                        }
                    ]
                },
                {
                    "slug": "gofile",
                    "name": "Gofile",
                    "icon": "<img src=\"/static/img/hoster_logos/gofile.svg\" class=\"fac-hoster\">",
                    "links": [
                        {
                            "name": "https://filecrypt.cc/Container/A149935E63",
                            "link": "https://filecrypt.cc/Container/A149935E63"
                        }
                    ]
                },
                {
                    "slug": "multiup",
                    "name": "MultiUp",
                    "icon": "<img src=\"/static/img/hoster_logos/multiup.png\" class=\"fac-hoster\">",
                    "links": [
                        {
                            "name": "https://filecrypt.cc/Container/4BCEAE2134",
                            "link": "https://filecrypt.cc/Container/4BCEAE2134"
                        }
                    ]
                }
            ],
            "PATCHES": [],
            "GOODIES": []
        },
        "can_vote": false
    },
    "SUCCESS": true
}