{
    "href": "/game/capitalism_2",
    "MSG": {
        "id": "1207658722",
        "title": "Capitalism 2",
        "slug": "capitalism_2",
        "thumb_id": "357b43ed454bb02d6a9d311d0ed9c625b6efac9eeed2e4244f900ad8f71bbbac",
        "bg_id": "daa09160f95dc4298442d3f4da66f836bf202311130b5b078a074067bae5e709",
        "url": "https://www.gog.com/game/capitalism_2",
        "developer": "Enlight Software",
        "publisher": "Enlight Software",
        "category": "Simulation",
        "uploading": "0",
        "last_upload": "1709553246",
        "votes": "1",
        "files": {
            "GAME": [
                {
                    "name": "setup_capitalism_2_1.14_(30032).exe",
                    "size": "163856272"
                }
            ],
            "PATCHES": [],
            "GOODIES": [
                {
                    "name": "manual.zip",
                    "size": "1179162"
                }
            ]
        },
        "links": {
            "GAME": [
                {
                    "slug": "1fichier",
                    "name": "1fichier",
                    "icon": "<img src=\"/static/img/hoster_logos/1fichier.svg\" class=\"fac-hoster\">",
                    "links": [
                        {
                            "name": "https://filecrypt.cc/Container/6836E28226",
                            "link": "https://filecrypt.cc/Container/6836E28226"
                        }
                    ]
                },
                {
                    "slug": "gofile",
                    "name": "Gofile",
                    "icon": "<img src=\"/static/img/hoster_logos/gofile.svg\" class=\"fac-hoster\">",
                    "links": [
                        {
                            "name": "https://filecrypt.cc/Container/E51835DE9A",
                            "link": "https://filecrypt.cc/Container/E51835DE9A"
                        }
                    ]
                },
                {
                    "slug": "multiup",
                    "name": "MultiUp",
                    "icon": "<img src=\"/static/img/hoster_logos/multiup.png\" class=\"fac-hoster\">",
                    "links": [
                        {
                            "name": "https://filecrypt.cc/Container/ACF5CB08AB",
                            "link": "https://filecrypt.cc/Container/ACF5CB08AB"
                        }
                    ]
                }
            ],
            "PATCHES": [],
            "GOODIES": [
                {
                    "slug": "1fichier",
                    "name": "1fichier",
                    "icon": "<img src=\"/static/img/hoster_logos/1fichier.svg\" class=\"fac-hoster\">",
                    "links": [
                        {
                            "name": "https://filecrypt.cc/Container/3AB32E268D",
                            "link": "https://filecrypt.cc/Container/3AB32E268D"
                        }
                    ]
                },
                {
                    "slug": "gofile",
                    "name": "Gofile",
                    "icon": "<img src=\"/static/img/hoster_logos/gofile.svg\" class=\"fac-hoster\">",
                    "links": [
                        {
                            "name": "https://filecrypt.cc/Container/43CB71E42C",
                            "link": "https://filecrypt.cc/Container/43CB71E42C"
                        }
                    ]
                },
                {
                    "slug": "multiup",
                    "name": "MultiUp",
                    "icon": "<img src=\"/static/img/hoster_logos/multiup.png\" class=\"fac-hoster\">",
                    "links": [
                        {
                            "name": "https://filecrypt.cc/Container/589CEBCAEB",
                            "link": "https://filecrypt.cc/Container/589CEBCAEB"
                        }
                    ]
                }
            ]
        },
        "can_vote": false
    },
    "SUCCESS": true
}