{
    "href": "/game/lorettas_brandnew_job",
    "MSG": {
        "id": "1597073672",
        "title": "Loretta's Brand-New Job",
        "slug": "lorettas_brandnew_job",
        "thumb_id": "0f5f42ed6f089a0da9caada080939f8d5e27ffb7e90c24bf4111eb6957c832a4",
        "bg_id": "27f5d833ebf37eafa2bec2427dee80356532f791a46646042b19e62733675782",
        "url": "https://www.gog.com/en/game/lorettas_brandnew_job",
        "developer": "AVANTGARDE",
        "publisher": "Kagura Games",
        "category": "Role-playing",
        "uploading": "0",
        "last_upload": "1695059943",
        "votes": "1",
        "files": {
            "GAME": [
                {
                    "name": "setup_lorettas_brand-new_job_unrated_v1_(en_1.00_cn_1.00)_(66175).exe",
                    "size": "689528136"
                },
                {
                    "name": "setup_lorettas_brand-new_job_v1_(en_1.00_cn_1.00)_(66175).exe",
                    "size": "437912232"
                }
            ],
            "PATCHES": [],
            "GOODIES": []
        },
        "links": {
            "GAME": [
                {
                    "slug": "sendcm",
                    "name": "Send.cm",
                    "icon": "<img src=\"/static/img/hoster_logos/sendcm.svg\" class=\"fac-hoster\">",
                    "links": [
                        {
                            "name": "https://filecrypt.cc/Container/752E1A98DE",
                            "link": "https://filecrypt.cc/Container/752E1A98DE"
                        }
                    ]
                },
                {
                    "slug": "1fichier",
                    "name": "1fichier",
                    "icon": "<img src=\"/static/img/hoster_logos/1fichier.svg\" class=\"fac-hoster\">",
                    "links": [
                        {
                            "name": "https://filecrypt.cc/Container/E049ADF9B0",
                            "link": "https://filecrypt.cc/Container/E049ADF9B0"
                        }
                    ]
                },
                {
                    "slug": "hexupload",
                    "name": "HexUpload",
                    "icon": "<img src=\"/static/img/hoster_logos/hexupload.svg\" class=\"fac-hoster\">",
                    "links": [
                        {
                            "name": "https://filecrypt.cc/Container/537F8E62B3",
                            "link": "https://filecrypt.cc/Container/537F8E62B3"
                        }
                    ]
                },
                {
                    "slug": "userscloud",
                    "name": "Userscloud",
                    "icon": "<img src=\"/static/img/hoster_logos/userscloud.svg\" class=\"fac-hoster\">",
                    "links": [
                        {
                            "name": "https://filecrypt.cc/Container/BE4B500F7D",
                            "link": "https://filecrypt.cc/Container/BE4B500F7D"
                        }
                    ]
                },
                {
                    "slug": "gofile",
                    "name": "Gofile",
                    "icon": "<img src=\"/static/img/hoster_logos/gofile.svg\" class=\"fac-hoster\">",
                    "links": [
                        {
                            "name": "https://filecrypt.cc/Container/8125ECD05D",
                            "link": "https://filecrypt.cc/Container/8125ECD05D"
                        }
                    ]
                },
                {
                    "slug": "multiup",
                    "name": "MultiUp",
                    "icon": "<img src=\"/static/img/hoster_logos/multiup.png\" class=\"fac-hoster\">",
                    "links": [
                        {
                            "name": "https://filecrypt.cc/Container/7A191F3B71",
                            "link": "https://filecrypt.cc/Container/7A191F3B71"
                        }
                    ]
                }
            ],
            "PATCHES": [],
            "GOODIES": []
        },
        "can_vote": true
    },
    "SUCCESS": true
}