{
    "href": "/game/lust_element_season_1",
    "MSG": {
        "id": "1618185450",
        "title": "Lust Element - Season 1",
        "slug": "lust_element_season_1",
        "thumb_id": "388aa42347e191a84b83902573938f0454cf94f3452555c1e22f01bfc14c804c",
        "bg_id": "dd4e92f6bdc6ed5e3da5dd11addb3551fea771943ad51bec1a157323f7d95826",
        "url": "https://www.gog.com/en/game/lust_element_season_1",
        "developer": "Night Icons",
        "publisher": "",
        "category": "Adventure",
        "uploading": "0",
        "last_upload": "1707451300",
        "votes": "1",
        "files": {
            "GAME": [
                {
                    "name": "setup_lust_element_-_season_1_0.6.1b002_(66453)-1.bin",
                    "size": "2172791489"
                },
                {
                    "name": "setup_lust_element_-_season_1_0.6.1b002_(66453).exe",
                    "size": "957520"
                }
            ],
            "PATCHES": [],
            "GOODIES": []
        },
        "links": {
            "GAME": [
                {
                    "slug": "sendcm",
                    "name": "Send.cm",
                    "icon": "<img src=\"/static/img/hoster_logos/sendcm.svg\" class=\"fac-hoster\">",
                    "links": [
                        {
                            "name": "https://filecrypt.cc/Container/B948106528",
                            "link": "https://filecrypt.cc/Container/B948106528"
                        }
                    ]
                },
                {
                    "slug": "1fichier",
                    "name": "1fichier",
                    "icon": "<img src=\"/static/img/hoster_logos/1fichier.svg\" class=\"fac-hoster\">",
                    "links": [
                        {
                            "name": "https://filecrypt.cc/Container/75715C1B8F",
                            "link": "https://filecrypt.cc/Container/75715C1B8F"
                        }
                    ]
                },
                {
                    "slug": "userscloud",
                    "name": "Userscloud",
                    "icon": "<img src=\"/static/img/hoster_logos/userscloud.svg\" class=\"fac-hoster\">",
                    "links": [
                        {
                            "name": "https://filecrypt.cc/Container/A64D729C54",
                            "link": "https://filecrypt.cc/Container/A64D729C54"
                        }
                    ]
                },
                {
                    "slug": "gofile",
                    "name": "Gofile",
                    "icon": "<img src=\"/static/img/hoster_logos/gofile.svg\" class=\"fac-hoster\">",
                    "links": [
                        {
                            "name": "https://filecrypt.cc/Container/51598E5A31",
                            "link": "https://filecrypt.cc/Container/51598E5A31"
                        }
                    ]
                },
                {
                    "slug": "multiup",
                    "name": "MultiUp",
                    "icon": "<img src=\"/static/img/hoster_logos/multiup.png\" class=\"fac-hoster\">",
                    "links": [
                        {
                            "name": "https://filecrypt.cc/Container/E329104354",
                            "link": "https://filecrypt.cc/Container/E329104354"
                        }
                    ]
                }
            ],
            "PATCHES": [],
            "GOODIES": []
        },
        "can_vote": true
    },
    "SUCCESS": true
}