{
    "href": "/game/ravenloft_stone_prophet",
    "MSG": {
        "id": "1432906190",
        "title": "Ravenloft: Stone Prophet",
        "slug": "ravenloft_stone_prophet",
        "thumb_id": "d92b8ec6c16ee140651189bda9a0623e0080205351f55fb93aa16544a213e3ca",
        "bg_id": "9f755b74be37404e022097f620f1524102df1581e01c720e16deadf97cb8df52",
        "url": "https://www.gog.com/game/dungeons_dragons_ravenloft_series",
        "developer": "DreamForge Intertainment",
        "publisher": "GOG",
        "category": "Role-playing",
        "uploading": "0",
        "last_upload": "1706156849",
        "votes": "1",
        "files": {
            "GAME": [
                {
                    "name": "setup_ravenloft_stone_prophet_1.1_cinefix_(45661).exe",
                    "size": "337187976"
                }
            ],
            "PATCHES": [],
            "GOODIES": [
                {
                    "name": "rl_stone_proph_cluebook_pdf.zip",
                    "size": "1177503"
                },
                {
                    "name": "rl_stone_proph_manual_pdf.zip",
                    "size": "1400351"
                }
            ]
        },
        "links": {
            "GAME": [
                {
                    "slug": "sendcm",
                    "name": "Send.cm",
                    "icon": "<img src=\"/static/img/hoster_logos/sendcm.svg\" class=\"fac-hoster\">",
                    "links": [
                        {
                            "name": "https://filecrypt.cc/Container/0A82FA0FE6",
                            "link": "https://filecrypt.cc/Container/0A82FA0FE6"
                        }
                    ]
                },
                {
                    "slug": "1fichier",
                    "name": "1fichier",
                    "icon": "<img src=\"/static/img/hoster_logos/1fichier.svg\" class=\"fac-hoster\">",
                    "links": [
                        {
                            "name": "https://filecrypt.cc/Container/40B22769C8",
                            "link": "https://filecrypt.cc/Container/40B22769C8"
                        }
                    ]
                },
                {
                    "slug": "userscloud",
                    "name": "Userscloud",
                    "icon": "<img src=\"/static/img/hoster_logos/userscloud.svg\" class=\"fac-hoster\">",
                    "links": [
                        {
                            "name": "https://filecrypt.cc/Container/95E910BCE4",
                            "link": "https://filecrypt.cc/Container/95E910BCE4"
                        }
                    ]
                },
                {
                    "slug": "gofile",
                    "name": "Gofile",
                    "icon": "<img src=\"/static/img/hoster_logos/gofile.svg\" class=\"fac-hoster\">",
                    "links": [
                        {
                            "name": "https://filecrypt.cc/Container/9D29B98BAA",
                            "link": "https://filecrypt.cc/Container/9D29B98BAA"
                        }
                    ]
                },
                {
                    "slug": "multiup",
                    "name": "MultiUp",
                    "icon": "<img src=\"/static/img/hoster_logos/multiup.png\" class=\"fac-hoster\">",
                    "links": [
                        {
                            "name": "https://filecrypt.cc/Container/23EAF5DD5B",
                            "link": "https://filecrypt.cc/Container/23EAF5DD5B"
                        }
                    ]
                }
            ],
            "PATCHES": [],
            "GOODIES": [
                {
                    "slug": "sendcm",
                    "name": "Send.cm",
                    "icon": "<img src=\"/static/img/hoster_logos/sendcm.svg\" class=\"fac-hoster\">",
                    "links": [
                        {
                            "name": "https://filecrypt.cc/Container/62EF7BA1E1",
                            "link": "https://filecrypt.cc/Container/62EF7BA1E1"
                        }
                    ]
                },
                {
                    "slug": "1fichier",
                    "name": "1fichier",
                    "icon": "<img src=\"/static/img/hoster_logos/1fichier.svg\" class=\"fac-hoster\">",
                    "links": [
                        {
                            "name": "https://filecrypt.cc/Container/BE0F646D40",
                            "link": "https://filecrypt.cc/Container/BE0F646D40"
                        }
                    ]
                },
                {
                    "slug": "userscloud",
                    "name": "Userscloud",
                    "icon": "<img src=\"/static/img/hoster_logos/userscloud.svg\" class=\"fac-hoster\">",
                    "links": [
                        {
                            "name": "https://filecrypt.cc/Container/9B6BE5CEE4",
                            "link": "https://filecrypt.cc/Container/9B6BE5CEE4"
                        }
                    ]
                },
                {
                    "slug": "gofile",
                    "name": "Gofile",
                    "icon": "<img src=\"/static/img/hoster_logos/gofile.svg\" class=\"fac-hoster\">",
                    "links": [
                        {
                            "name": "https://filecrypt.cc/Container/971C0B9829",
                            "link": "https://filecrypt.cc/Container/971C0B9829"
                        }
                    ]
                },
                {
                    "slug": "multiup",
                    "name": "MultiUp",
                    "icon": "<img src=\"/static/img/hoster_logos/multiup.png\" class=\"fac-hoster\">",
                    "links": [
                        {
                            "name": "https://filecrypt.cc/Container/89C5BD8129",
                            "link": "https://filecrypt.cc/Container/89C5BD8129"
                        }
                    ]
                }
            ]
        },
        "can_vote": true
    },
    "SUCCESS": true
}