{
    "href": "/game/sensible_world_of_soccer_9697",
    "MSG": {
        "id": "1207659176",
        "title": "Sensible World of Soccer 96/97",
        "slug": "sensible_world_of_soccer_9697",
        "thumb_id": "44245179eddb526519c2cba329fa46dc50890fec30966cfccd055752a45947c7",
        "bg_id": "ac5e29bf14e1fb739dde91f0f9a565ce0ba8932d3fd58ad1aac50f7439abf845",
        "url": "https://www.gog.com/game/sensible_world_of_soccer_9697",
        "developer": "Sensible Software",
        "publisher": "Codemasters",
        "category": "Sports",
        "uploading": "0",
        "last_upload": "1709694172",
        "votes": "1",
        "files": {
            "GAME": [
                {
                    "name": "setup_sensible_world_of_soccer_96-97_1.0_(28045).exe",
                    "size": "311679024"
                }
            ],
            "PATCHES": [],
            "GOODIES": [
                {
                    "name": "swos_9697_manual.zip",
                    "size": "88845357"
                }
            ]
        },
        "links": {
            "GAME": [
                {
                    "slug": "1fichier",
                    "name": "1fichier",
                    "icon": "<img src=\"/static/img/hoster_logos/1fichier.svg\" class=\"fac-hoster\">",
                    "links": [
                        {
                            "name": "https://filecrypt.cc/Container/9C42E267BB",
                            "link": "https://filecrypt.cc/Container/9C42E267BB"
                        }
                    ]
                },
                {
                    "slug": "gofile",
                    "name": "Gofile",
                    "icon": "<img src=\"/static/img/hoster_logos/gofile.svg\" class=\"fac-hoster\">",
                    "links": [
                        {
                            "name": "https://filecrypt.cc/Container/9ACF8A9D48",
                            "link": "https://filecrypt.cc/Container/9ACF8A9D48"
                        }
                    ]
                },
                {
                    "slug": "multiup",
                    "name": "MultiUp",
                    "icon": "<img src=\"/static/img/hoster_logos/multiup.png\" class=\"fac-hoster\">",
                    "links": [
                        {
                            "name": "https://filecrypt.cc/Container/94C6CD3DB8",
                            "link": "https://filecrypt.cc/Container/94C6CD3DB8"
                        }
                    ]
                }
            ],
            "PATCHES": [],
            "GOODIES": [
                {
                    "slug": "1fichier",
                    "name": "1fichier",
                    "icon": "<img src=\"/static/img/hoster_logos/1fichier.svg\" class=\"fac-hoster\">",
                    "links": [
                        {
                            "name": "https://filecrypt.cc/Container/ECDD4B7EE8",
                            "link": "https://filecrypt.cc/Container/ECDD4B7EE8"
                        }
                    ]
                },
                {
                    "slug": "gofile",
                    "name": "Gofile",
                    "icon": "<img src=\"/static/img/hoster_logos/gofile.svg\" class=\"fac-hoster\">",
                    "links": [
                        {
                            "name": "https://filecrypt.cc/Container/42DBF30539",
                            "link": "https://filecrypt.cc/Container/42DBF30539"
                        }
                    ]
                },
                {
                    "slug": "multiup",
                    "name": "MultiUp",
                    "icon": "<img src=\"/static/img/hoster_logos/multiup.png\" class=\"fac-hoster\">",
                    "links": [
                        {
                            "name": "https://filecrypt.cc/Container/6576CFC721",
                            "link": "https://filecrypt.cc/Container/6576CFC721"
                        }
                    ]
                }
            ]
        },
        "can_vote": false
    },
    "SUCCESS": true
}