{
    "href": "/game/spelljammer_pirates_of_realmspace",
    "MSG": {
        "id": "1582445378",
        "title": "Spelljammer: Pirates of Realmspace",
        "slug": "spelljammer_pirates_of_realmspace",
        "thumb_id": "53ae24063c8580cf646c9fa47a8b799167019e22eb38a87b615d4d7957029cba",
        "bg_id": "71a2e83bb9cc0edfed2cb8d99a05093041837ac52ea470a53e703c9a0f882770",
        "url": "https://www.gog.com/en/game/spelljammer_pirates_of_realmspace",
        "developer": "Cybertech",
        "publisher": "SNEG",
        "category": "Role-playing",
        "uploading": "0",
        "last_upload": "1706792501",
        "votes": "1",
        "files": {
            "GAME": [
                {
                    "name": "setup_spelljammer_pirates_of_realmspace_2.3_(63421).exe",
                    "size": "46149880"
                }
            ],
            "PATCHES": [],
            "GOODIES": [
                {
                    "name": "spelljammer_pirates_of_realmspace_manuals.zip",
                    "size": "160610123"
                }
            ]
        },
        "links": {
            "GAME": [
                {
                    "slug": "sendcm",
                    "name": "Send.cm",
                    "icon": "<img src=\"/static/img/hoster_logos/sendcm.svg\" class=\"fac-hoster\">",
                    "links": [
                        {
                            "name": "https://filecrypt.cc/Container/346A076DBA",
                            "link": "https://filecrypt.cc/Container/346A076DBA"
                        }
                    ]
                },
                {
                    "slug": "1fichier",
                    "name": "1fichier",
                    "icon": "<img src=\"/static/img/hoster_logos/1fichier.svg\" class=\"fac-hoster\">",
                    "links": [
                        {
                            "name": "https://filecrypt.cc/Container/72B797847E",
                            "link": "https://filecrypt.cc/Container/72B797847E"
                        }
                    ]
                },
                {
                    "slug": "userscloud",
                    "name": "Userscloud",
                    "icon": "<img src=\"/static/img/hoster_logos/userscloud.svg\" class=\"fac-hoster\">",
                    "links": [
                        {
                            "name": "https://filecrypt.cc/Container/BAAB262388",
                            "link": "https://filecrypt.cc/Container/BAAB262388"
                        }
                    ]
                },
                {
                    "slug": "gofile",
                    "name": "Gofile",
                    "icon": "<img src=\"/static/img/hoster_logos/gofile.svg\" class=\"fac-hoster\">",
                    "links": [
                        {
                            "name": "https://filecrypt.cc/Container/F9376B18EE",
                            "link": "https://filecrypt.cc/Container/F9376B18EE"
                        }
                    ]
                },
                {
                    "slug": "multiup",
                    "name": "MultiUp",
                    "icon": "<img src=\"/static/img/hoster_logos/multiup.png\" class=\"fac-hoster\">",
                    "links": [
                        {
                            "name": "https://filecrypt.cc/Container/513E2D514F",
                            "link": "https://filecrypt.cc/Container/513E2D514F"
                        }
                    ]
                }
            ],
            "PATCHES": [],
            "GOODIES": [
                {
                    "slug": "sendcm",
                    "name": "Send.cm",
                    "icon": "<img src=\"/static/img/hoster_logos/sendcm.svg\" class=\"fac-hoster\">",
                    "links": [
                        {
                            "name": "https://filecrypt.cc/Container/F5DA75691B",
                            "link": "https://filecrypt.cc/Container/F5DA75691B"
                        }
                    ]
                },
                {
                    "slug": "1fichier",
                    "name": "1fichier",
                    "icon": "<img src=\"/static/img/hoster_logos/1fichier.svg\" class=\"fac-hoster\">",
                    "links": [
                        {
                            "name": "https://filecrypt.cc/Container/5144DEB04D",
                            "link": "https://filecrypt.cc/Container/5144DEB04D"
                        }
                    ]
                },
                {
                    "slug": "userscloud",
                    "name": "Userscloud",
                    "icon": "<img src=\"/static/img/hoster_logos/userscloud.svg\" class=\"fac-hoster\">",
                    "links": [
                        {
                            "name": "https://filecrypt.cc/Container/953DC02C4B",
                            "link": "https://filecrypt.cc/Container/953DC02C4B"
                        }
                    ]
                },
                {
                    "slug": "gofile",
                    "name": "Gofile",
                    "icon": "<img src=\"/static/img/hoster_logos/gofile.svg\" class=\"fac-hoster\">",
                    "links": [
                        {
                            "name": "https://filecrypt.cc/Container/00C93D86B0",
                            "link": "https://filecrypt.cc/Container/00C93D86B0"
                        }
                    ]
                },
                {
                    "slug": "multiup",
                    "name": "MultiUp",
                    "icon": "<img src=\"/static/img/hoster_logos/multiup.png\" class=\"fac-hoster\">",
                    "links": [
                        {
                            "name": "https://filecrypt.cc/Container/2A7EE1F1D3",
                            "link": "https://filecrypt.cc/Container/2A7EE1F1D3"
                        }
                    ]
                }
            ]
        },
        "can_vote": true
    },
    "SUCCESS": true
}