{
    "href": "/game/the_sojourn",
    "MSG": {
        "id": "1813140866",
        "title": "The Sojourn",
        "slug": "the_sojourn",
        "thumb_id": "956f1ee6f2fdf12a5ea896547750d0fff3d4f1af684f1bb3ba77462c0dbb7a10",
        "bg_id": "131c2180877d167f203435f806159d8668f1d5a7d563c9eff19db1edd562ae91",
        "url": "https://www.gog.com/game/the_sojourn",
        "developer": "Shifting Tides",
        "publisher": "Iceberg Interactive",
        "category": "Adventure",
        "uploading": "0",
        "last_upload": "1700357366",
        "votes": "1",
        "files": {
            "GAME": [
                {
                    "name": "setup_the_sojourn_1.1_(64bit)_(41585)-1.bin",
                    "size": "2464510097"
                },
                {
                    "name": "setup_the_sojourn_1.1_(64bit)_(41585).exe",
                    "size": "813344"
                }
            ],
            "PATCHES": [],
            "GOODIES": [
                {
                    "name": "prototype_equilibrium_artbook.zip",
                    "size": "42556272"
                },
                {
                    "name": "the_sojourn_artbook.zip",
                    "size": "173145587"
                },
                {
                    "name": "the_sojourn_early_prototype_equilibrium.zip",
                    "size": "521555239"
                },
                {
                    "name": "the_sojourn_original_soundtrack_flac.zip",
                    "size": "239601518"
                },
                {
                    "name": "the_sojourn_original_soundtrack_mp3.zip",
                    "size": "117939379"
                }
            ]
        },
        "links": {
            "GAME": [
                {
                    "slug": "sendcm",
                    "name": "Send.cm",
                    "icon": "<img src=\"/static/img/hoster_logos/sendcm.svg\" class=\"fac-hoster\">",
                    "links": [
                        {
                            "name": "https://filecrypt.cc/Container/37C0C5455D",
                            "link": "https://filecrypt.cc/Container/37C0C5455D"
                        }
                    ]
                },
                {
                    "slug": "1fichier",
                    "name": "1fichier",
                    "icon": "<img src=\"/static/img/hoster_logos/1fichier.svg\" class=\"fac-hoster\">",
                    "links": [
                        {
                            "name": "https://filecrypt.cc/Container/6015ECEF77",
                            "link": "https://filecrypt.cc/Container/6015ECEF77"
                        }
                    ]
                },
                {
                    "slug": "userscloud",
                    "name": "Userscloud",
                    "icon": "<img src=\"/static/img/hoster_logos/userscloud.svg\" class=\"fac-hoster\">",
                    "links": [
                        {
                            "name": "https://filecrypt.cc/Container/5379C04013",
                            "link": "https://filecrypt.cc/Container/5379C04013"
                        }
                    ]
                },
                {
                    "slug": "gofile",
                    "name": "Gofile",
                    "icon": "<img src=\"/static/img/hoster_logos/gofile.svg\" class=\"fac-hoster\">",
                    "links": [
                        {
                            "name": "https://filecrypt.cc/Container/7A1653981A",
                            "link": "https://filecrypt.cc/Container/7A1653981A"
                        }
                    ]
                },
                {
                    "slug": "multiup",
                    "name": "MultiUp",
                    "icon": "<img src=\"/static/img/hoster_logos/multiup.png\" class=\"fac-hoster\">",
                    "links": [
                        {
                            "name": "https://filecrypt.cc/Container/ED7DC9DDD6",
                            "link": "https://filecrypt.cc/Container/ED7DC9DDD6"
                        }
                    ]
                }
            ],
            "PATCHES": [],
            "GOODIES": [
                {
                    "slug": "sendcm",
                    "name": "Send.cm",
                    "icon": "<img src=\"/static/img/hoster_logos/sendcm.svg\" class=\"fac-hoster\">",
                    "links": [
                        {
                            "name": "https://filecrypt.cc/Container/F6301D6FEB",
                            "link": "https://filecrypt.cc/Container/F6301D6FEB"
                        }
                    ]
                },
                {
                    "slug": "1fichier",
                    "name": "1fichier",
                    "icon": "<img src=\"/static/img/hoster_logos/1fichier.svg\" class=\"fac-hoster\">",
                    "links": [
                        {
                            "name": "https://filecrypt.cc/Container/3B38545485",
                            "link": "https://filecrypt.cc/Container/3B38545485"
                        }
                    ]
                },
                {
                    "slug": "userscloud",
                    "name": "Userscloud",
                    "icon": "<img src=\"/static/img/hoster_logos/userscloud.svg\" class=\"fac-hoster\">",
                    "links": [
                        {
                            "name": "https://filecrypt.cc/Container/4F1B2A0173",
                            "link": "https://filecrypt.cc/Container/4F1B2A0173"
                        }
                    ]
                },
                {
                    "slug": "gofile",
                    "name": "Gofile",
                    "icon": "<img src=\"/static/img/hoster_logos/gofile.svg\" class=\"fac-hoster\">",
                    "links": [
                        {
                            "name": "https://filecrypt.cc/Container/AE376494B3",
                            "link": "https://filecrypt.cc/Container/AE376494B3"
                        }
                    ]
                },
                {
                    "slug": "multiup",
                    "name": "MultiUp",
                    "icon": "<img src=\"/static/img/hoster_logos/multiup.png\" class=\"fac-hoster\">",
                    "links": [
                        {
                            "name": "https://filecrypt.cc/Container/428F2A820C",
                            "link": "https://filecrypt.cc/Container/428F2A820C"
                        }
                    ]
                }
            ]
        },
        "can_vote": true
    },
    "SUCCESS": true
}