{
    "href": "/game/the_invisible_hand",
    "MSG": {
        "id": "1867580454",
        "title": "The Invisible Hand",
        "slug": "the_invisible_hand",
        "thumb_id": "52b3de8ca519a76f4b5baa50dcadef16df94ef64b11ccb24afaf1155674b7c73",
        "bg_id": "ba4625b4a9f63f8266658dc51d49754fa0934839d28ddf95168dcb343737c740",
        "url": "https://www.gog.com/game/the_invisible_hand",
        "developer": "Power Struggle Games",
        "publisher": "Fellow Traveller",
        "category": "Simulation",
        "uploading": "0",
        "last_upload": "1705445776",
        "votes": "1",
        "files": {
            "GAME": [
                {
                    "name": "setup_the_invisible_hand_1.2.2_(67551).exe",
                    "size": "1120729432"
                }
            ],
            "PATCHES": [],
            "GOODIES": [
                {
                    "name": "The_Invisible_Hand_OST_MP3.zip",
                    "size": "82542380"
                },
                {
                    "name": "The_Invisible_Hand_OST_WAV.zip",
                    "size": "314298168"
                }
            ]
        },
        "links": {
            "GAME": [
                {
                    "slug": "1fichier",
                    "name": "1fichier",
                    "icon": "<img src=\"/static/img/hoster_logos/1fichier.svg\" class=\"fac-hoster\">",
                    "links": [
                        {
                            "name": "https://filecrypt.cc/Container/876A518C33",
                            "link": "https://filecrypt.cc/Container/876A518C33"
                        }
                    ]
                },
                {
                    "slug": "userscloud",
                    "name": "Userscloud",
                    "icon": "<img src=\"/static/img/hoster_logos/userscloud.svg\" class=\"fac-hoster\">",
                    "links": [
                        {
                            "name": "https://filecrypt.cc/Container/530A3C1FFA",
                            "link": "https://filecrypt.cc/Container/530A3C1FFA"
                        }
                    ]
                },
                {
                    "slug": "gofile",
                    "name": "Gofile",
                    "icon": "<img src=\"/static/img/hoster_logos/gofile.svg\" class=\"fac-hoster\">",
                    "links": [
                        {
                            "name": "https://filecrypt.cc/Container/FB2212EFCB",
                            "link": "https://filecrypt.cc/Container/FB2212EFCB"
                        }
                    ]
                },
                {
                    "slug": "multiup",
                    "name": "MultiUp",
                    "icon": "<img src=\"/static/img/hoster_logos/multiup.png\" class=\"fac-hoster\">",
                    "links": [
                        {
                            "name": "https://filecrypt.cc/Container/679D685045",
                            "link": "https://filecrypt.cc/Container/679D685045"
                        }
                    ]
                }
            ],
            "PATCHES": [],
            "GOODIES": [
                {
                    "slug": "1fichier",
                    "name": "1fichier",
                    "icon": "<img src=\"/static/img/hoster_logos/1fichier.svg\" class=\"fac-hoster\">",
                    "links": [
                        {
                            "name": "https://filecrypt.cc/Container/24D9C3AED9",
                            "link": "https://filecrypt.cc/Container/24D9C3AED9"
                        }
                    ]
                },
                {
                    "slug": "userscloud",
                    "name": "Userscloud",
                    "icon": "<img src=\"/static/img/hoster_logos/userscloud.svg\" class=\"fac-hoster\">",
                    "links": [
                        {
                            "name": "https://filecrypt.cc/Container/4FF68FC98A",
                            "link": "https://filecrypt.cc/Container/4FF68FC98A"
                        }
                    ]
                },
                {
                    "slug": "gofile",
                    "name": "Gofile",
                    "icon": "<img src=\"/static/img/hoster_logos/gofile.svg\" class=\"fac-hoster\">",
                    "links": [
                        {
                            "name": "https://filecrypt.cc/Container/CC4776D342",
                            "link": "https://filecrypt.cc/Container/CC4776D342"
                        }
                    ]
                },
                {
                    "slug": "multiup",
                    "name": "MultiUp",
                    "icon": "<img src=\"/static/img/hoster_logos/multiup.png\" class=\"fac-hoster\">",
                    "links": [
                        {
                            "name": "https://filecrypt.cc/Container/2693B317AB",
                            "link": "https://filecrypt.cc/Container/2693B317AB"
                        }
                    ]
                }
            ]
        },
        "can_vote": true
    },
    "SUCCESS": true
}