{
    "href": "/game/the_fantastic_kitty_rue",
    "MSG": {
        "id": "1733107106",
        "title": "The Fantastic Kitty Rue",
        "slug": "the_fantastic_kitty_rue",
        "thumb_id": "50a5dfdbdd871663ce842535c26fe202b60e5ea8d2c0a7811f9a6355d78110f5",
        "bg_id": "f8165a5c6b93a035c18c08e90840f6b7319df0b53ad66ecbe7f54df7e6a9d763",
        "url": "https://www.gog.com/en/game/the_fantastic_kitty_rue",
        "developer": "Ink Rose Inc, Studio Syndicat, TYM Studio",
        "publisher": "Ink Rose Inc",
        "category": "Adventure",
        "uploading": "0",
        "last_upload": "1704571543",
        "votes": "1",
        "files": {
            "GAME": [
                {
                    "name": "setup_the_fantastic_kitty_rue_1.0_(64bit)_(61676).exe",
                    "size": "1404836216"
                }
            ],
            "PATCHES": [],
            "GOODIES": []
        },
        "links": {
            "GAME": [
                {
                    "slug": "sendcm",
                    "name": "Send.cm",
                    "icon": "<img src=\"/static/img/hoster_logos/sendcm.svg\" class=\"fac-hoster\">",
                    "links": [
                        {
                            "name": "https://filecrypt.cc/Container/2F0B339D12",
                            "link": "https://filecrypt.cc/Container/2F0B339D12"
                        }
                    ]
                },
                {
                    "slug": "1fichier",
                    "name": "1fichier",
                    "icon": "<img src=\"/static/img/hoster_logos/1fichier.svg\" class=\"fac-hoster\">",
                    "links": [
                        {
                            "name": "https://filecrypt.cc/Container/17B1E47446",
                            "link": "https://filecrypt.cc/Container/17B1E47446"
                        }
                    ]
                },
                {
                    "slug": "userscloud",
                    "name": "Userscloud",
                    "icon": "<img src=\"/static/img/hoster_logos/userscloud.svg\" class=\"fac-hoster\">",
                    "links": [
                        {
                            "name": "https://filecrypt.cc/Container/5F1B8A5C10",
                            "link": "https://filecrypt.cc/Container/5F1B8A5C10"
                        }
                    ]
                },
                {
                    "slug": "gofile",
                    "name": "Gofile",
                    "icon": "<img src=\"/static/img/hoster_logos/gofile.svg\" class=\"fac-hoster\">",
                    "links": [
                        {
                            "name": "https://filecrypt.cc/Container/7FA0CE1219",
                            "link": "https://filecrypt.cc/Container/7FA0CE1219"
                        }
                    ]
                },
                {
                    "slug": "multiup",
                    "name": "MultiUp",
                    "icon": "<img src=\"/static/img/hoster_logos/multiup.png\" class=\"fac-hoster\">",
                    "links": [
                        {
                            "name": "https://filecrypt.cc/Container/9748D6125E",
                            "link": "https://filecrypt.cc/Container/9748D6125E"
                        }
                    ]
                }
            ],
            "PATCHES": [],
            "GOODIES": []
        },
        "can_vote": true
    },
    "SUCCESS": true
}