{
    "href": "/game/trenches_world_war_1_horror_survival_game",
    "MSG": {
        "id": "2133979138",
        "title": "Trenches - World War 1 Horror Survival Game",
        "slug": "trenches_world_war_1_horror_survival_game",
        "thumb_id": "64b240ca6984e52d649b29526d79787b4cee1f97e87db0ca3a38b6885b0cab98",
        "bg_id": "66f4f307f83d15b3454e9b3880d1d4991966de47420cb1540bf1cdde1795360b",
        "url": "https://www.gog.com/en/game/trenches_world_war_1_horror_survival_game",
        "developer": "Steelkrill Studio",
        "publisher": "Steelkrill Studio",
        "category": "Adventure",
        "uploading": "0",
        "last_upload": "1695662038",
        "votes": "1",
        "files": {
            "GAME": [
                {
                    "name": "setup_trenches_-_world_war_1_horror_survival_game_v2.4_(65294).exe",
                    "size": "397593672"
                }
            ],
            "PATCHES": [],
            "GOODIES": []
        },
        "links": {
            "GAME": [
                {
                    "slug": "sendcm",
                    "name": "Send.cm",
                    "icon": "<img src=\"/static/img/hoster_logos/sendcm.svg\" class=\"fac-hoster\">",
                    "links": [
                        {
                            "name": "https://filecrypt.cc/Container/E28CE2D5ED",
                            "link": "https://filecrypt.cc/Container/E28CE2D5ED"
                        }
                    ]
                },
                {
                    "slug": "1fichier",
                    "name": "1fichier",
                    "icon": "<img src=\"/static/img/hoster_logos/1fichier.svg\" class=\"fac-hoster\">",
                    "links": [
                        {
                            "name": "https://filecrypt.cc/Container/56539DF796",
                            "link": "https://filecrypt.cc/Container/56539DF796"
                        }
                    ]
                },
                {
                    "slug": "hexupload",
                    "name": "HexUpload",
                    "icon": "<img src=\"/static/img/hoster_logos/hexupload.svg\" class=\"fac-hoster\">",
                    "links": [
                        {
                            "name": "https://filecrypt.cc/Container/77AC9A16C6",
                            "link": "https://filecrypt.cc/Container/77AC9A16C6"
                        }
                    ]
                },
                {
                    "slug": "userscloud",
                    "name": "Userscloud",
                    "icon": "<img src=\"/static/img/hoster_logos/userscloud.svg\" class=\"fac-hoster\">",
                    "links": [
                        {
                            "name": "https://filecrypt.cc/Container/256436F837",
                            "link": "https://filecrypt.cc/Container/256436F837"
                        }
                    ]
                },
                {
                    "slug": "gofile",
                    "name": "Gofile",
                    "icon": "<img src=\"/static/img/hoster_logos/gofile.svg\" class=\"fac-hoster\">",
                    "links": [
                        {
                            "name": "https://filecrypt.cc/Container/6590E4F8F0",
                            "link": "https://filecrypt.cc/Container/6590E4F8F0"
                        }
                    ]
                }
            ],
            "PATCHES": [],
            "GOODIES": []
        },
        "can_vote": true
    },
    "SUCCESS": true
}