{
    "href": "/game/war_wind_ii_human_onslaught",
    "MSG": {
        "id": "1441098222",
        "title": "War Wind II: Human Onslaught",
        "slug": "war_wind_ii_human_onslaught",
        "thumb_id": "322bf185802a52875a67db23f2a0ab12e68a9164973a0efea7031ce4374cde5f",
        "bg_id": "f3caa5d3b69a278f51e60c7a331000f02f44556a6c7561ef2b3458a1d2723195",
        "url": "https://www.gog.com/game/war_wind_ii_human_onslaught",
        "developer": "DreamForge Intertainment",
        "publisher": "GOG",
        "category": "Strategy",
        "uploading": "0",
        "last_upload": "1707292886",
        "votes": "1",
        "files": {
            "GAME": [
                {
                    "name": "setup_war_wind2_2.0.0.4.exe",
                    "size": "435158904"
                }
            ],
            "PATCHES": [],
            "GOODIES": [
                {
                    "name": "war_wind_2_dependency_charts.zip",
                    "size": "5954253"
                },
                {
                    "name": "war_wind_2_manual.zip",
                    "size": "2977986"
                }
            ]
        },
        "links": {
            "GAME": [
                {
                    "slug": "sendcm",
                    "name": "Send.cm",
                    "icon": "<img src=\"/static/img/hoster_logos/sendcm.svg\" class=\"fac-hoster\">",
                    "links": [
                        {
                            "name": "https://filecrypt.cc/Container/2F60392404",
                            "link": "https://filecrypt.cc/Container/2F60392404"
                        }
                    ]
                },
                {
                    "slug": "1fichier",
                    "name": "1fichier",
                    "icon": "<img src=\"/static/img/hoster_logos/1fichier.svg\" class=\"fac-hoster\">",
                    "links": [
                        {
                            "name": "https://filecrypt.cc/Container/39310537BB",
                            "link": "https://filecrypt.cc/Container/39310537BB"
                        }
                    ]
                },
                {
                    "slug": "userscloud",
                    "name": "Userscloud",
                    "icon": "<img src=\"/static/img/hoster_logos/userscloud.svg\" class=\"fac-hoster\">",
                    "links": [
                        {
                            "name": "https://filecrypt.cc/Container/A859C8E678",
                            "link": "https://filecrypt.cc/Container/A859C8E678"
                        }
                    ]
                },
                {
                    "slug": "gofile",
                    "name": "Gofile",
                    "icon": "<img src=\"/static/img/hoster_logos/gofile.svg\" class=\"fac-hoster\">",
                    "links": [
                        {
                            "name": "https://filecrypt.cc/Container/C0CAEEA616",
                            "link": "https://filecrypt.cc/Container/C0CAEEA616"
                        }
                    ]
                },
                {
                    "slug": "multiup",
                    "name": "MultiUp",
                    "icon": "<img src=\"/static/img/hoster_logos/multiup.png\" class=\"fac-hoster\">",
                    "links": [
                        {
                            "name": "https://filecrypt.cc/Container/8E243FE726",
                            "link": "https://filecrypt.cc/Container/8E243FE726"
                        }
                    ]
                }
            ],
            "PATCHES": [],
            "GOODIES": [
                {
                    "slug": "sendcm",
                    "name": "Send.cm",
                    "icon": "<img src=\"/static/img/hoster_logos/sendcm.svg\" class=\"fac-hoster\">",
                    "links": [
                        {
                            "name": "https://filecrypt.cc/Container/97F31FFB6A",
                            "link": "https://filecrypt.cc/Container/97F31FFB6A"
                        }
                    ]
                },
                {
                    "slug": "1fichier",
                    "name": "1fichier",
                    "icon": "<img src=\"/static/img/hoster_logos/1fichier.svg\" class=\"fac-hoster\">",
                    "links": [
                        {
                            "name": "https://filecrypt.cc/Container/E439B8CA00",
                            "link": "https://filecrypt.cc/Container/E439B8CA00"
                        }
                    ]
                },
                {
                    "slug": "userscloud",
                    "name": "Userscloud",
                    "icon": "<img src=\"/static/img/hoster_logos/userscloud.svg\" class=\"fac-hoster\">",
                    "links": [
                        {
                            "name": "https://filecrypt.cc/Container/8053B12A98",
                            "link": "https://filecrypt.cc/Container/8053B12A98"
                        }
                    ]
                },
                {
                    "slug": "gofile",
                    "name": "Gofile",
                    "icon": "<img src=\"/static/img/hoster_logos/gofile.svg\" class=\"fac-hoster\">",
                    "links": [
                        {
                            "name": "https://filecrypt.cc/Container/C6E269ED6F",
                            "link": "https://filecrypt.cc/Container/C6E269ED6F"
                        }
                    ]
                },
                {
                    "slug": "multiup",
                    "name": "MultiUp",
                    "icon": "<img src=\"/static/img/hoster_logos/multiup.png\" class=\"fac-hoster\">",
                    "links": [
                        {
                            "name": "https://filecrypt.cc/Container/147008D487",
                            "link": "https://filecrypt.cc/Container/147008D487"
                        }
                    ]
                }
            ]
        },
        "can_vote": true
    },
    "SUCCESS": true
}